dargparser/__init__.py
dargparser/helpers.py
dargparser/parsing.py
dargparser/version.py
dargparser-1.3.0.dist-info/LICENSE
dargparser-1.3.0.dist-info/METADATA
dargparser-1.3.0.dist-info/WHEEL
dargparser-1.3.0.dist-info/entry_points.txt
dargparser-1.3.0.dist-info/top_level.txt
dargparser-1.3.0.dist-info/zip-safe
dargparser-1.3.0.dist-info/RECORD
