Metadata-Version: 2.1
Name: dargparser
Version: 1.3.0
Summary: A lean and hackable typed argument parser for Python.
Home-page: https://github.com/konstantinjdobler/dargparser
Project-URL: Bug Tracker, https://github.com/konstantinjdobler/dargparser/issues
Project-URL: Changelog, https://github.com/konstantinjdobler/dargparser/releases
Classifier: Programming Language :: Python :: 3.7
Classifier: Programming Language :: Python :: 3.8
Classifier: Programming Language :: Python :: 3.9
Classifier: Programming Language :: Python :: 3.10
Classifier: Programming Language :: Python :: 3.11
Classifier: License :: OSI Approved :: Apache Software License
Classifier: Intended Audience :: Developers
Requires-Python: >=3.7
License-File: LICENSE
Provides-Extra: dev
Requires-Dist: black ; extra == 'dev'
Requires-Dist: flake8 ; extra == 'dev'
Requires-Dist: isort ; extra == 'dev'
